azure/mgmt/network/__init__.py
azure/mgmt/network/_configuration.py
azure/mgmt/network/_network_management_client.py
azure/mgmt/network/_patch.py
azure/mgmt/network/_version.py
azure/mgmt/network/py.typed
azure/mgmt/network/_utils/__init__.py
azure/mgmt/network/_utils/serialization.py
azure/mgmt/network/_utils/utils.py
azure/mgmt/network/aio/__init__.py
azure/mgmt/network/aio/_configuration.py
azure/mgmt/network/aio/_network_management_client.py
azure/mgmt/network/aio/_patch.py
azure/mgmt/network/aio/operations/__init__.py
azure/mgmt/network/aio/operations/_operations.py
azure/mgmt/network/aio/operations/_patch.py
azure/mgmt/network/models/__init__.py
azure/mgmt/network/models/_models_py3.py
azure/mgmt/network/models/_network_management_client_enums.py
azure/mgmt/network/models/_patch.py
azure/mgmt/network/operations/__init__.py
azure/mgmt/network/operations/_operations.py
azure/mgmt/network/operations/_patch.py
azure_mgmt_network-30.0.0.dist-info/licenses/LICENSE
azure_mgmt_network-30.0.0.dist-info/METADATA
azure_mgmt_network-30.0.0.dist-info/WHEEL
azure_mgmt_network-30.0.0.dist-info/top_level.txt
azure_mgmt_network-30.0.0.dist-info/RECORD
